{"_path":"/android/lesson7/query","_dir":"lesson7","_draft":false,"_partial":false,"_locale":"","title":"Room. Query","description":"У цьому уроці поговоримо докладніше про Query. У якому вигляді ми можемо отримувати дані: List, масив, Cursor, LiveData. Як передавати параметри. Як отримувати тільки деякі поля. Як за допомогою Query виконувати update і delete запити в Room.","body":{"type":"root","children":[{"type":"element","tag":"h1","props":{"id":"room-query"},"children":[{"type":"text","value":"Room. Query"}]},{"type":"element","tag":"p","props":{},"children":[{"type":"text","value":"У цьому уроці поговоримо докладніше про "},{"type":"element","tag":"code","props":{"className":[]},"children":[{"type":"text","value":"Query"}]},{"type":"text","value":". У якому вигляді ми можемо отримувати дані: "},{"type":"element","tag":"code","props":{"className":[]},"children":[{"type":"text","value":"List"}]},{"type":"text","value":", масив, "},{"type":"element","tag":"code","props":{"className":[]},"children":[{"type":"text","value":"Cursor"}]},{"type":"text","value":", "},{"type":"element","tag":"code","props":{"className":[]},"children":[{"type":"text","value":"LiveData"}]},{"type":"text","value":". Як передавати параметри. Як отримувати тільки деякі поля. Як за допомогою "},{"type":"element","tag":"code","props":{"className":[]},"children":[{"type":"text","value":"Query"}]},{"type":"text","value":" виконувати "},{"type":"element","tag":"code","props":{"className":[]},"children":[{"type":"text","value":"update"}]},{"type":"text","value":" і "},{"type":"element","tag":"code","props":{"className":[]},"children":[{"type":"text","value":"delete"}]},{"type":"text","value":" запити в Room."}]},{"type":"element","tag":"p","props":{},"children":[{"type":"text","value":"Як приклад будемо працювати з таким "},{"type":"element","tag":"code","props":{"className":[]},"children":[{"type":"text","value":"Entity"}]},{"type":"text","value":" класом:"}]},{"type":"element","tag":"pre","props":{"className":"language-java shiki shiki-themes github-dark github-light monokai","code":"@Entity()\npublic class Employee {\n \n   @PrimaryKey()\n   public long id;\n \n   @ColumnInfo(name = \"first_name\")\n   public String firstName;\n \n   @ColumnInfo(name = \"last_name\")\n   public String lastName;\n \n   public int salary;\n \n}\n","language":"java","meta":"","style":""},"children":[{"type":"element","tag":"code","props":{"__ignoreMap":""},"children":[{"type":"element","tag":"span","props":{"class":"line","line":1},"children":[{"type":"element","tag":"span","props":{"style":"--shiki-dark:#E1E4E8;--shiki-default:#24292E;--shiki-sepia:#F8F8F2"},"children":[{"type":"text","value":"@"}]},{"type":"element","tag":"span","props":{"style":"--shiki-dark:#F97583;--shiki-dark-font-style:inherit;--shiki-default:#D73A49;--shiki-default-font-style:inherit;--shiki-sepia:#66D9EF;--shiki-sepia-font-style:italic"},"children":[{"type":"text","value":"Entity"}]},{"type":"element","tag":"span","props":{"style":"--shiki-dark:#E1E4E8;--shiki-default:#24292E;--shiki-sepia:#F8F8F2"},"children":[{"type":"text","value":"()\n"}]}]},{"type":"element","tag":"span","props":{"class":"line","line":2},"children":[{"type":"element","tag":"span","props":{"style":"--shiki-dark:#F97583;--shiki-default:#D73A49;--shiki-sepia:#F92672"},"children":[{"type":"text","value":"public"}]},{"type":"element","tag":"span","props":{"style":"--shiki-dark:#F97583;--shiki-default:#D73A49;--shiki-sepia:#F92672"},"children":[{"type":"text","value":" class"}]},{"type":"element","tag":"span","props":{"style":"--shiki-dark:#B392F0;--shiki-dark-text-decoration:inherit;--shiki-default:#6F42C1;--shiki-default-text-decoration:inherit;--shiki-sepia:#A6E22E;--shiki-sepia-text-decoration:underline"},"children":[{"type":"text","value":" Employee"}]},{"type":"element","tag":"span","props":{"style":"--shiki-dark:#E1E4E8;--shiki-default:#24292E;--shiki-sepia:#F8F8F2"},"children":[{"type":"text","value":" {\n"}]}]},{"type":"element","tag":"span","props":{"class":"line","line":3},"children":[{"type":"element","tag":"span","props":{"style":"--shiki-dark:#E1E4E8;--shiki-default:#24292E;--shiki-sepia:#F8F8F2"},"children":[{"type":"text","value":" \n"}]}]},{"type":"element","tag":"span","props":{"class":"line","line":4},"children":[{"type":"element","tag":"span","props":{"style":"--shiki-dark:#E1E4E8;--shiki-default:#24292E;--shiki-sepia:#F8F8F2"},"children":[{"type":"text","value":"   @"}]},{"type":"element","tag":"span","props":{"style":"--shiki-dark:#F97583;--shiki-dark-font-style:inherit;--shiki-default:#D73A49;--shiki-default-font-style:inherit;--shiki-sepia:#66D9EF;--shiki-sepia-font-style:italic"},"children":[{"type":"text","value":"PrimaryKey"}]},{"type":"element","tag":"span","props":{"style":"--shiki-dark:#E1E4E8;--shiki-default:#24292E;--shiki-sepia:#F8F8F2"},"children":[{"type":"text","value":"()\n"}]}]},{"type":"element","tag":"span","props":{"class":"line","line":5},"children":[{"type":"element","tag":"span","props":{"style":"--shiki-dark:#F97583;--shiki-default:#D73A49;--shiki-sepia:#F92672"},"children":[{"type":"text","value":"   public"}]},{"type":"element","tag":"span","props":{"style":"--shiki-dark:#F97583;--shiki-dark-font-style:inherit;--shiki-default:#D73A49;--shiki-default-font-style:inherit;--shiki-sepia:#66D9EF;--shiki-sepia-font-style:italic"},"children":[{"type":"text","value":" long"}]},{"type":"element","tag":"span","props":{"style":"--shiki-dark:#E1E4E8;--shiki-default:#24292E;--shiki-sepia:#F8F8F2"},"children":[{"type":"text","value":" id;\n"}]}]},{"type":"element","tag":"span","props":{"class":"line","line":6},"children":[{"type":"element","tag":"span","props":{"style":"--shiki-dark:#E1E4E8;--shiki-default:#24292E;--shiki-sepia:#F8F8F2"},"children":[{"type":"text","value":" \n"}]}]},{"type":"element","tag":"span","props":{"class":"line","line":7},"children":[{"type":"element","tag":"span","props":{"style":"--shiki-dark:#E1E4E8;--shiki-default:#24292E;--shiki-sepia:#F8F8F2"},"children":[{"type":"text","value":"   @"}]},{"type":"element","tag":"span","props":{"style":"--shiki-dark:#F97583;--shiki-dark-font-style:inherit;--shiki-default:#D73A49;--shiki-default-font-style:inherit;--shiki-sepia:#66D9EF;--shiki-sepia-font-style:italic"},"children":[{"type":"text","value":"ColumnInfo"}]},{"type":"element","tag":"span","props":{"style":"--shiki-dark:#E1E4E8;--shiki-default:#24292E;--shiki-sepia:#F8F8F2"},"children":[{"type":"text","value":"("}]},{"type":"element","tag":"span","props":{"style":"--shiki-dark:#79B8FF;--shiki-default:#005CC5;--shiki-sepia:#AE81FF"},"children":[{"type":"text","value":"name"}]},{"type":"element","tag":"span","props":{"style":"--shiki-dark:#F97583;--shiki-default:#D73A49;--shiki-sepia:#F92672"},"children":[{"type":"text","value":" ="}]},{"type":"element","tag":"span","props":{"style":"--shiki-dark:#9ECBFF;--shiki-default:#032F62;--shiki-sepia:#E6DB74"},"children":[{"type":"text","value":" \"first_name\""}]},{"type":"element","tag":"span","props":{"style":"--shiki-dark:#E1E4E8;--shiki-default:#24292E;--shiki-sepia:#F8F8F2"},"children":[{"type":"text","value":")\n"}]}]},{"type":"element","tag":"span","props":{"class":"line","line":8},"children":[{"type":"element","tag":"span","props":{"style":"--shiki-dark:#F97583;--shiki-default:#D73A49;--shiki-sepia:#F92672"},"children":[{"type":"text","value":"   public"}]},{"type":"element","tag":"span","props":{"style":"--shiki-dark:#E1E4E8;--shiki-dark-font-style:inherit;--shiki-default:#24292E;--shiki-default-font-style:inherit;--shiki-sepia:#66D9EF;--shiki-sepia-font-style:italic"},"children":[{"type":"text","value":" String"}]},{"type":"element","tag":"span","props":{"style":"--shiki-dark:#E1E4E8;--shiki-default:#24292E;--shiki-sepia:#F8F8F2"},"children":[{"type":"text","value":" firstName;\n"}]}]},{"type":"element","tag":"span","props":{"class":"line","line":9},"children":[{"type":"element","tag":"span","props":{"style":"--shiki-dark:#E1E4E8;--shiki-default:#24292E;--shiki-sepia:#F8F8F2"},"children":[{"type":"text","value":" \n"}]}]},{"type":"element","tag":"span","props":{"class":"line","line":10},"children":[{"type":"element","tag":"span","props":{"style":"--shiki-dark:#E1E4E8;--shiki-default:#24292E;--shiki-sepia:#F8F8F2"},"children":[{"type":"text","value":"   @"}]},{"type":"element","tag":"span","props":{"style":"--shiki-dark:#F97583;--shiki-dark-font-style:inherit;--shiki-default:#D73A49;--shiki-default-font-style:inherit;--shiki-sepia:#66D9EF;--shiki-sepia-font-style:italic"},"children":[{"type":"text","value":"ColumnInfo"}]},{"type":"element","tag":"span","props":{"style":"--shiki-dark:#E1E4E8;--shiki-default:#24292E;--shiki-sepia:#F8F8F2"},"children":[{"type":"text","value":"("}]},{"type":"element","tag":"span","props":{"style":"--shiki-dark:#79B8FF;--shiki-default:#005CC5;--shiki-sepia:#AE81FF"},"children":[{"type":"text","value":"name"}]},{"type":"element","tag":"span","props":{"style":"--shiki-dark:#F97583;--shiki-default:#D73A49;--shiki-sepia:#F92672"},"children":[{"type":"text","value":" ="}]},{"type":"element","tag":"span","props":{"style":"--shiki-dark:#9ECBFF;--shiki-default:#032F62;--shiki-sepia:#E6DB74"},"children":[{"type":"text","value":" \"last_name\""}]},{"type":"element","tag":"span","props":{"style":"--shiki-dark:#E1E4E8;--shiki-default:#24292E;--shiki-sepia:#F8F8F2"},"children":[{"type":"text","value":")\n"}]}]},{"type":"element","tag":"span","props":{"class":"line","line":11},"children":[{"type":"element","tag":"span","props":{"style":"--shiki-dark:#F97583;--shiki-default:#D73A49;--shiki-sepia:#F92672"},"children":[{"type":"text","value":"   public"}]},{"type":"element","tag":"span","props":{"style":"--shiki-dark:#E1E4E8;--shiki-dark-font-style:inherit;--shiki-default:#24292E;--shiki-default-font-style:inherit;--shiki-sepia:#66D9EF;--shiki-sepia-font-style:italic"},"children":[{"type":"text","value":" String"}]},{"type":"element","tag":"span","props":{"style":"--shiki-dark:#E1E4E8;--shiki-default:#24292E;--shiki-sepia:#F8F8F2"},"children":[{"type":"text","value":" lastName;\n"}]}]},{"type":"element","tag":"span","props":{"class":"line","line":12},"children":[{"type":"element","tag":"span","props":{"style":"--shiki-dark:#E1E4E8;--shiki-default:#24292E;--shiki-sepia:#F8F8F2"},"children":[{"type":"text","value":" \n"}]}]},{"type":"element","tag":"span","props":{"class":"line","line":13},"children":[{"type":"element","tag":"span","props":{"style":"--shiki-dark:#F97583;--shiki-default:#D73A49;--shiki-sepia:#F92672"},"children":[{"type":"text","value":"   public"}]},{"type":"element","tag":"span","props":{"style":"--shiki-dark:#F97583;--shiki-dark-font-style:inherit;--shiki-default:#D73A49;--shiki-default-font-style:inherit;--shiki-sepia:#66D9EF;--shiki-sepia-font-style:italic"},"children":[{"type":"text","value":" int"}]},{"type":"element","tag":"span","props":{"style":"--shiki-dark:#E1E4E8;--shiki-default:#24292E;--shiki-sepia:#F8F8F2"},"children":[{"type":"text","value":" salary;\n"}]}]},{"type":"element","tag":"span","props":{"class":"line","line":14},"children":[{"type":"element","tag":"span","props":{"style":"--shiki-dark:#E1E4E8;--shiki-default:#24292E;--shiki-sepia:#F8F8F2"},"children":[{"type":"text","value":" \n"}]}]},{"type":"element","tag":"span","props":{"class":"line","line":15},"children":[{"type":"element","tag":"span","props":{"style":"--shiki-dark:#E1E4E8;--shiki-default:#24292E;--shiki-sepia:#F8F8F2"},"children":[{"type":"text","value":"}\n"}]}]}]}]},{"type":"element","tag":"h2","props":{"id":"list-масив-cursor"},"children":[{"type":"text","value":"List, масив, Cursor"}]},{"type":"element","tag":"p","props":{},"children":[{"type":"text","value":"Щоб запросити з бази "},{"type":"element","tag":"code","props":{"className":[]},"children":[{"type":"text","value":"Employee"}]},{"type":"text","value":"-об'єкти, необхідно в "},{"type":"element","tag":"code","props":{"className":[]},"children":[{"type":"text","value":"Dao"}]},{"type":"text","value":" створити метод з анотацією "},{"type":"element","tag":"code","props":{"className":[]},"children":[{"type":"text","value":"Query"}]}]},{"type":"element","tag":"pre","props":{"className":"language-java shiki shiki-themes github-dark github-light monokai","code":"@Dao\npublic interface EmployeeDao {\n \n   @Query(\"SELECT * FROM employee\")\n   List<Employee> getAll();\n \n   // ...\n \n}\n","language":"java","meta":"","style":""},"children":[{"type":"element","tag":"code","props":{"__ignoreMap":""},"children":[{"type":"element","tag":"span","props":{"class":"line","line":1},"children":[{"type":"element","tag":"span","props":{"style":"--shiki-dark:#E1E4E8;--shiki-default:#24292E;--shiki-sepia:#F8F8F2"},"children":[{"type":"text","value":"@"}]},{"type":"element","tag":"span","props":{"style":"--shiki-dark:#F97583;--shiki-dark-font-style:inherit;--shiki-default:#D73A49;--shiki-default-font-style:inherit;--shiki-sepia:#66D9EF;--shiki-sepia-font-style:italic"},"children":[{"type":"text","value":"Dao\n"}]}]},{"type":"element","tag":"span","props":{"class":"line","line":2},"children":[{"type":"element","tag":"span","props":{"style":"--shiki-dark:#F97583;--shiki-default:#D73A49;--shiki-sepia:#F92672"},"children":[{"type":"text","value":"public"}]},{"type":"element","tag":"span","props":{"style":"--shiki-dark:#F97583;--shiki-default:#D73A49;--shiki-sepia:#F92672"},"children":[{"type":"text","value":" interface"}]},{"type":"element","tag":"span","props":{"style":"--shiki-dark:#B392F0;--shiki-dark-text-decoration:inherit;--shiki-default:#6F42C1;--shiki-default-text-decoration:inherit;--shiki-sepia:#A6E22E;--shiki-sepia-text-decoration:underline"},"children":[{"type":"text","value":" EmployeeDao"}]},{"type":"element","tag":"span","props":{"style":"--shiki-dark:#E1E4E8;--shiki-default:#24292E;--shiki-sepia:#F8F8F2"},"children":[{"type":"text","value":" {\n"}]}]},{"type":"element","tag":"span","props":{"class":"line","line":3},"children":[{"type":"element","tag":"span","props":{"style":"--shiki-dark:#E1E4E8;--shiki-default:#24292E;--shiki-sepia:#F8F8F2"},"children":[{"type":"text","value":" \n"}]}]},{"type":"element","tag":"span","props":{"class":"line","line":4},"children":[{"type":"element","tag":"span","props":{"style":"--shiki-dark:#E1E4E8;--shiki-default:#24292E;--shiki-sepia:#F8F8F2"},"children":[{"type":"text","value":"   @"}]},{"type":"element","tag":"span","props":{"style":"--shiki-dark:#F97583;--shiki-dark-font-style:inherit;--shiki-default:#D73A49;--shiki-default-font-style:inherit;--shiki-sepia:#66D9EF;--shiki-sepia-font-style:italic"},"children":[{"type":"text","value":"Query"}]},{"type":"element","tag":"span","props":{"style":"--shiki-dark:#E1E4E8;--shiki-default:#24292E;--shiki-sepia:#F8F8F2"},"children":[{"type":"text","value":"("}]},{"type":"element","tag":"span","props":{"style":"--shiki-dark:#9ECBFF;--shiki-default:#032F62;--shiki-sepia:#E6DB74"},"children":[{"type":"text","value":"\"SELECT * FROM employee\""}]},{"type":"element","tag":"span","props":{"style":"--shiki-dark:#E1E4E8;--shiki-default:#24292E;--shiki-sepia:#F8F8F2"},"children":[{"type":"text","value":")\n"}]}]},{"type":"element","tag":"span","props":{"class":"line","line":5},"children":[{"type":"element","tag":"span","props":{"style":"--shiki-dark:#E1E4E8;--shiki-dark-font-style:inherit;--shiki-default:#24292E;--shiki-default-font-style:inherit;--shiki-sepia:#66D9EF;--shiki-sepia-font-style:italic"},"children":[{"type":"text","value":"   List"}]},{"type":"element","tag":"span","props":{"style":"--shiki-dark:#E1E4E8;--shiki-default:#24292E;--shiki-sepia:#F8F8F2"},"children":[{"type":"text","value":"<"}]},{"type":"element","tag":"span","props":{"style":"--shiki-dark:#F97583;--shiki-dark-font-style:inherit;--shiki-default:#D73A49;--shiki-default-font-style:inherit;--shiki-sepia:#66D9EF;--shiki-sepia-font-style:italic"},"children":[{"type":"text","value":"Employee"}]},{"type":"element","tag":"span","props":{"style":"--shiki-dark:#E1E4E8;--shiki-default:#24292E;--shiki-sepia:#F8F8F2"},"children":[{"type":"text","value":"> "}]},{"type":"element","tag":"span","props":{"style":"--shiki-dark:#B392F0;--shiki-default:#6F42C1;--shiki-sepia:#A6E22E"},"children":[{"type":"text","value":"getAll"}]},{"type":"element","tag":"span","props":{"style":"--shiki-dark:#E1E4E8;--shiki-default:#24292E;--shiki-sepia:#F8F8F2"},"children":[{"type":"text","value":"();\n"}]}]},{"type":"element","tag":"span","props":{"class":"line","line":6},"children":[{"type":"element","tag":"span","props":{"style":"--shiki-dark:#E1E4E8;--shiki-default:#24292E;--shiki-sepia:#F8F8F2"},"children":[{"type":"text","value":" \n"}]}]},{"type":"element","tag":"span","props":{"class":"line","line":7},"children":[{"type":"element","tag":"span","props":{"style":"--shiki-dark:#6A737D;--shiki-default:#6A737D;--shiki-sepia:#88846F"},"children":[{"type":"text","value":"   // ...\n"}]}]},{"type":"element","tag":"span","props":{"class":"line","line":8},"children":[{"type":"element","tag":"span","props":{"style":"--shiki-dark:#E1E4E8;--shiki-default:#24292E;--shiki-sepia:#F8F8F2"},"children":[{"type":"text","value":" \n"}]}]},{"type":"element","tag":"span","props":{"class":"line","line":9},"children":[{"type":"element","tag":"span","props":{"style":"--shiki-dark:#E1E4E8;--shiki-default:#24292E;--shiki-sepia:#F8F8F2"},"children":[{"type":"text","value":"}\n"}]}]}]}]},{"type":"element","tag":"p","props":{},"children":[{"type":"text","value":"У "},{"type":"element","tag":"code","props":{"className":[]},"children":[{"type":"text","value":"Query"}]},{"type":"text","value":" прописуємо запит, який має повернути дані. А як тип, що повертається, вказуємо List"},{"type":"element","tag":"employee","props":{},"children":[{"type":"text","value":"."}]}]},{"type":"element","tag":"p","props":{},"children":[{"type":"text","value":"Під час виклику цього методу Room зробить запит у таблицю employee, конвертує отримані дані в "},{"type":"element","tag":"code","props":{"className":[]},"children":[{"type":"text","value":"Employee"}]},{"type":"text","value":" об'єкти й упакує їх у "},{"type":"element","tag":"code","props":{"className":[]},"children":[{"type":"text","value":"List"}]},{"type":"text","value":"."}]},{"type":"element","tag":"p","props":{},"children":[{"type":"text","value":"Запит, який ви вказуєте в "},{"type":"element","tag":"code","props":{"className":[]},"children":[{"type":"text","value":"Query"}]},{"type":"text","value":", перевіряється на правильність синтаксису під час компіляції. Якщо в ньому буде помилка, система вам одразу підкаже це."}]},{"type":"element","tag":"p","props":{},"children":[{"type":"text","value":"Замість "},{"type":"element","tag":"code","props":{"className":[]},"children":[{"type":"text","value":"List"}]},{"type":"text","value":", ми також можемо використовувати масив:"}]},{"type":"element","tag":"pre","props":{"className":"language-java shiki shiki-themes github-dark github-light monokai","code":"@Query(\"SELECT * FROM employee\")\nEmployee[] getAll();\n","language":"java","meta":"","style":""},"children":[{"type":"element","tag":"code","props":{"__ignoreMap":""},"children":[{"type":"element","tag":"span","props":{"class":"line","line":1},"children":[{"type":"element","tag":"span","props":{"style":"--shiki-dark:#E1E4E8;--shiki-default:#24292E;--shiki-sepia:#F8F8F2"},"children":[{"type":"text","value":"@"}]},{"type":"element","tag":"span","props":{"style":"--shiki-dark:#F97583;--shiki-dark-font-style:inherit;--shiki-default:#D73A49;--shiki-default-font-style:inherit;--shiki-sepia:#66D9EF;--shiki-sepia-font-style:italic"},"children":[{"type":"text","value":"Query"}]},{"type":"element","tag":"span","props":{"style":"--shiki-dark:#E1E4E8;--shiki-default:#24292E;--shiki-sepia:#F8F8F2"},"children":[{"type":"text","value":"("}]},{"type":"element","tag":"span","props":{"style":"--shiki-dark:#9ECBFF;--shiki-default:#032F62;--shiki-sepia:#E6DB74"},"children":[{"type":"text","value":"\"SELECT * FROM employee\""}]},{"type":"element","tag":"span","props":{"style":"--shiki-dark:#E1E4E8;--shiki-default:#24292E;--shiki-sepia:#F8F8F2"},"children":[{"type":"text","value":")\n"}]}]},{"type":"element","tag":"span","props":{"class":"line","line":2},"children":[{"type":"element","tag":"span","props":{"style":"--shiki-dark:#F97583;--shiki-dark-font-style:inherit;--shiki-default:#D73A49;--shiki-default-font-style:inherit;--shiki-sepia:#66D9EF;--shiki-sepia-font-style:italic"},"children":[{"type":"text","value":"Employee"}]},{"type":"element","tag":"span","props":{"style":"--shiki-dark:#E1E4E8;--shiki-default:#24292E;--shiki-sepia:#F8F8F2"},"children":[{"type":"text","value":"[] "}]},{"type":"element","tag":"span","props":{"style":"--shiki-dark:#B392F0;--shiki-default:#6F42C1;--shiki-sepia:#A6E22E"},"children":[{"type":"text","value":"getAll"}]},{"type":"element","tag":"span","props":{"style":"--shiki-dark:#E1E4E8;--shiki-default:#24292E;--shiki-sepia:#F8F8F2"},"children":[{"type":"text","value":"();\n"}]}]}]}]},{"type":"element","tag":"p","props":{},"children":[{"type":"text","value":"і навіть "},{"type":"element","tag":"code","props":{"className":[]},"children":[{"type":"text","value":"Cursor"}]},{"type":"text","value":", якщо це необхідно з якихось причин:"}]},{"type":"element","tag":"pre","props":{"className":"language-java shiki shiki-themes github-dark github-light monokai","code":"@Query(\"SELECT * FROM employee\")\nCursor getAll();\n","language":"java","meta":"","style":""},"children":[{"type":"element","tag":"code","props":{"__ignoreMap":""},"children":[{"type":"element","tag":"span","props":{"class":"line","line":1},"children":[{"type":"element","tag":"span","props":{"style":"--shiki-dark:#E1E4E8;--shiki-default:#24292E;--shiki-sepia:#F8F8F2"},"children":[{"type":"text","value":"@"}]},{"type":"element","tag":"span","props":{"style":"--shiki-dark:#F97583;--shiki-dark-font-style:inherit;--shiki-default:#D73A49;--shiki-default-font-style:inherit;--shiki-sepia:#66D9EF;--shiki-sepia-font-style:italic"},"children":[{"type":"text","value":"Query"}]},{"type":"element","tag":"span","props":{"style":"--shiki-dark:#E1E4E8;--shiki-default:#24292E;--shiki-sepia:#F8F8F2"},"children":[{"type":"text","value":"("}]},{"type":"element","tag":"span","props":{"style":"--shiki-dark:#9ECBFF;--shiki-default:#032F62;--shiki-sepia:#E6DB74"},"children":[{"type":"text","value":"\"SELECT * FROM employee\""}]},{"type":"element","tag":"span","props":{"style":"--shiki-dark:#E1E4E8;--shiki-default:#24292E;--shiki-sepia:#F8F8F2"},"children":[{"type":"text","value":")\n"}]}]},{"type":"element","tag":"span","props":{"class":"line","line":2},"children":[{"type":"element","tag":"span","props":{"style":"--shiki-dark:#E1E4E8;--shiki-dark-font-style:inherit;--shiki-default:#24292E;--shiki-default-font-style:inherit;--shiki-sepia:#66D9EF;--shiki-sepia-font-style:italic"},"children":[{"type":"text","value":"Cursor"}]},{"type":"element","tag":"span","props":{"style":"--shiki-dark:#B392F0;--shiki-default:#6F42C1;--shiki-sepia:#A6E22E"},"children":[{"type":"text","value":" getAll"}]},{"type":"element","tag":"span","props":{"style":"--shiki-dark:#E1E4E8;--shiki-default:#24292E;--shiki-sepia:#F8F8F2"},"children":[{"type":"text","value":"();\n"}]}]}]}]},{"type":"element","tag":"p","props":{},"children":[{"type":"element","tag":"code","props":{"className":[]},"children":[{"type":"text","value":"LiveData"}]},{"type":"element","tag":"code","props":{"className":[]},"children":[{"type":"text","value":"Room"}]},{"type":"text","value":" вміє повертати дані в "},{"type":"element","tag":"code","props":{"className":[]},"children":[{"type":"text","value":"LiveData"}]},{"type":"text","value":" обгортці."}]},{"type":"element","tag":"pre","props":{"className":"language-java shiki shiki-themes github-dark github-light monokai","code":"@Query(\"SELECT * FROM employee\")\nLiveData<List<Employee>> getAll();\n","language":"java","meta":"","style":""},"children":[{"type":"element","tag":"code","props":{"__ignoreMap":""},"children":[{"type":"element","tag":"span","props":{"class":"line","line":1},"children":[{"type":"element","tag":"span","props":{"style":"--shiki-dark:#E1E4E8;--shiki-default:#24292E;--shiki-sepia:#F8F8F2"},"children":[{"type":"text","value":"@"}]},{"type":"element","tag":"span","props":{"style":"--shiki-dark:#F97583;--shiki-dark-font-style:inherit;--shiki-default:#D73A49;--shiki-default-font-style:inherit;--shiki-sepia:#66D9EF;--shiki-sepia-font-style:italic"},"children":[{"type":"text","value":"Query"}]},{"type":"element","tag":"span","props":{"style":"--shiki-dark:#E1E4E8;--shiki-default:#24292E;--shiki-sepia:#F8F8F2"},"children":[{"type":"text","value":"("}]},{"type":"element","tag":"span","props":{"style":"--shiki-dark:#9ECBFF;--shiki-default:#032F62;--shiki-sepia:#E6DB74"},"children":[{"type":"text","value":"\"SELECT * FROM employee\""}]},{"type":"element","tag":"span","props":{"style":"--shiki-dark:#E1E4E8;--shiki-default:#24292E;--shiki-sepia:#F8F8F2"},"children":[{"type":"text","value":")\n"}]}]},{"type":"element","tag":"span","props":{"class":"line","line":2},"children":[{"type":"element","tag":"span","props":{"style":"--shiki-dark:#E1E4E8;--shiki-dark-font-style:inherit;--shiki-default:#24292E;--shiki-default-font-style:inherit;--shiki-sepia:#66D9EF;--shiki-sepia-font-style:italic"},"children":[{"type":"text","value":"LiveData"}]},{"type":"element","tag":"span","props":{"style":"--shiki-dark:#F97583;--shiki-default:#D73A49;--shiki-sepia:#F92672"},"children":[{"type":"text","value":"<"}]},{"type":"element","tag":"span","props":{"style":"--shiki-dark:#E1E4E8;--shiki-dark-font-style:inherit;--shiki-default:#24292E;--shiki-default-font-style:inherit;--shiki-sepia:#66D9EF;--shiki-sepia-font-style:italic"},"children":[{"type":"text","value":"List"}]},{"type":"element","tag":"span","props":{"style":"--shiki-dark:#F97583;--shiki-default:#D73A49;--shiki-sepia:#F92672"},"children":[{"type":"text","value":"<"}]},{"type":"element","tag":"span","props":{"style":"--shiki-dark:#E1E4E8;--shiki-default:#24292E;--shiki-sepia:#F8F8F2"},"children":[{"type":"text","value":"Employee"}]},{"type":"element","tag":"span","props":{"style":"--shiki-dark:#F97583;--shiki-default:#D73A49;--shiki-sepia:#F92672"},"children":[{"type":"text","value":">>"}]},{"type":"element","tag":"span","props":{"style":"--shiki-dark:#B392F0;--shiki-default:#6F42C1;--shiki-sepia:#A6E22E"},"children":[{"type":"text","value":" getAll"}]},{"type":"element","tag":"span","props":{"style":"--shiki-dark:#E1E4E8;--shiki-default:#24292E;--shiki-sepia:#F8F8F2"},"children":[{"type":"text","value":"();\n"}]}]}]}]},{"type":"element","tag":"p","props":{},"children":[{"type":"text","value":"Отримання даних у коді Activity має такий вигляд:"}]},{"type":"element","tag":"pre","props":{"className":"language-java shiki shiki-themes github-dark github-light monokai","code":"LiveData<List<Employee>> employeesLiveData = db.employeeDao().getAll();\n \nemployeesLiveData.observe(this, new Observer<List<Employee>>() {\n   @Override\n   public void onChanged(@Nullable List<Employee> employees) {\n       log(\"onChanged \" + employees);\n   }\n});\n","language":"java","meta":"","style":""},"children":[{"type":"element","tag":"code","props":{"__ignoreMap":""},"children":[{"type":"element","tag":"span","props":{"class":"line","line":1},"children":[{"type":"element","tag":"span","props":{"style":"--shiki-dark:#E1E4E8;--shiki-dark-font-style:inherit;--shiki-default:#24292E;--shiki-default-font-style:inherit;--shiki-sepia:#66D9EF;--shiki-sepia-font-style:italic"},"children":[{"type":"text","value":"LiveData"}]},{"type":"element","tag":"span","props":{"style":"--shiki-dark:#E1E4E8;--shiki-default:#24292E;--shiki-sepia:#F8F8F2"},"children":[{"type":"text","value":"<"}]},{"type":"element","tag":"span","props":{"style":"--shiki-dark:#E1E4E8;--shiki-dark-font-style:inherit;--shiki-default:#24292E;--shiki-default-font-style:inherit;--shiki-sepia:#66D9EF;--shiki-sepia-font-style:italic"},"children":[{"type":"text","value":"List"}]},{"type":"element","tag":"span","props":{"style":"--shiki-dark:#E1E4E8;--shiki-default:#24292E;--shiki-sepia:#F8F8F2"},"children":[{"type":"text","value":"<"}]},{"type":"element","tag":"span","props":{"style":"--shiki-dark:#F97583;--shiki-dark-font-style:inherit;--shiki-default:#D73A49;--shiki-default-font-style:inherit;--shiki-sepia:#66D9EF;--shiki-sepia-font-style:italic"},"children":[{"type":"text","value":"Employee"}]},{"type":"element","tag":"span","props":{"style":"--shiki-dark:#E1E4E8;--shiki-default:#24292E;--shiki-sepia:#F8F8F2"},"children":[{"type":"text","value":">> employeesLiveData "}]},{"type":"element","tag":"span","props":{"style":"--shiki-dark:#F97583;--shiki-default:#D73A49;--shiki-sepia:#F92672"},"children":[{"type":"text","value":"="}]},{"type":"element","tag":"span","props":{"style":"--shiki-dark:#E1E4E8;--shiki-default:#24292E;--shiki-sepia:#F8F8F2"},"children":[{"type":"text","value":" db."}]},{"type":"element","tag":"span","props":{"style":"--shiki-dark:#B392F0;--shiki-default:#6F42C1;--shiki-sepia:#A6E22E"},"children":[{"type":"text","value":"employeeDao"}]},{"type":"element","tag":"span","props":{"style":"--shiki-dark:#E1E4E8;--shiki-default:#24292E;--shiki-sepia:#F8F8F2"},"children":[{"type":"text","value":"()."}]},{"type":"element","tag":"span","props":{"style":"--shiki-dark:#B392F0;--shiki-default:#6F42C1;--shiki-sepia:#A6E22E"},"children":[{"type":"text","value":"getAll"}]},{"type":"element","tag":"span","props":{"style":"--shiki-dark:#E1E4E8;--shiki-default:#24292E;--shiki-sepia:#F8F8F2"},"children":[{"type":"text","value":"();\n"}]}]},{"type":"element","tag":"span","props":{"class":"line","line":2},"children":[{"type":"element","tag":"span","props":{"style":"--shiki-dark:#E1E4E8;--shiki-default:#24292E;--shiki-sepia:#F8F8F2"},"children":[{"type":"text","value":" \n"}]}]},{"type":"element","tag":"span","props":{"class":"line","line":3},"children":[{"type":"element","tag":"span","props":{"style":"--shiki-dark:#E1E4E8;--shiki-default:#24292E;--shiki-sepia:#F8F8F2"},"children":[{"type":"text","value":"employeesLiveData."}]},{"type":"element","tag":"span","props":{"style":"--shiki-dark:#B392F0;--shiki-default:#6F42C1;--shiki-sepia:#A6E22E"},"children":[{"type":"text","value":"observe"}]},{"type":"element","tag":"span","props":{"style":"--shiki-dark:#E1E4E8;--shiki-default:#24292E;--shiki-sepia:#F8F8F2"},"children":[{"type":"text","value":"("}]},{"type":"element","tag":"span","props":{"style":"--shiki-dark:#79B8FF;--shiki-default:#005CC5;--shiki-sepia:#FD971F"},"children":[{"type":"text","value":"this"}]},{"type":"element","tag":"span","props":{"style":"--shiki-dark:#E1E4E8;--shiki-default:#24292E;--shiki-sepia:#F8F8F2"},"children":[{"type":"text","value":", "}]},{"type":"element","tag":"span","props":{"style":"--shiki-dark:#F97583;--shiki-default:#D73A49;--shiki-sepia:#F92672"},"children":[{"type":"text","value":"new"}]},{"type":"element","tag":"span","props":{"style":"--shiki-dark:#E1E4E8;--shiki-dark-font-style:inherit;--shiki-default:#24292E;--shiki-default-font-style:inherit;--shiki-sepia:#66D9EF;--shiki-sepia-font-style:italic"},"children":[{"type":"text","value":" Observer"}]},{"type":"element","tag":"span","props":{"style":"--shiki-dark:#E1E4E8;--shiki-default:#24292E;--shiki-sepia:#F8F8F2"},"children":[{"type":"text","value":"<"}]},{"type":"element","tag":"span","props":{"style":"--shiki-dark:#E1E4E8;--shiki-dark-font-style:inherit;--shiki-default:#24292E;--shiki-default-font-style:inherit;--shiki-sepia:#66D9EF;--shiki-sepia-font-style:italic"},"children":[{"type":"text","value":"List"}]},{"type":"element","tag":"span","props":{"style":"--shiki-dark:#E1E4E8;--shiki-default:#24292E;--shiki-sepia:#F8F8F2"},"children":[{"type":"text","value":"<"}]},{"type":"element","tag":"span","props":{"style":"--shiki-dark:#F97583;--shiki-dark-font-style:inherit;--shiki-default:#D73A49;--shiki-default-font-style:inherit;--shiki-sepia:#66D9EF;--shiki-sepia-font-style:italic"},"children":[{"type":"text","value":"Employee"}]},{"type":"element","tag":"span","props":{"style":"--shiki-dark:#E1E4E8;--shiki-default:#24292E;--shiki-sepia:#F8F8F2"},"children":[{"type":"text","value":">>() {\n"}]}]},{"type":"element","tag":"span","props":{"class":"line","line":4},"children":[{"type":"element","tag":"span","props":{"style":"--shiki-dark:#E1E4E8;--shiki-default:#24292E;--shiki-sepia:#F8F8F2"},"children":[{"type":"text","value":"   @"}]},{"type":"element","tag":"span","props":{"style":"--shiki-dark:#F97583;--shiki-dark-font-style:inherit;--shiki-default:#D73A49;--shiki-default-font-style:inherit;--shiki-sepia:#66D9EF;--shiki-sepia-font-style:italic"},"children":[{"type":"text","value":"Override\n"}]}]},{"type":"element","tag":"span","props":{"class":"line","line":5},"children":[{"type":"element","tag":"span","props":{"style":"--shiki-dark:#F97583;--shiki-default:#D73A49;--shiki-sepia:#F92672"},"children":[{"type":"text","value":"   public"}]},{"type":"element","tag":"span","props":{"style":"--shiki-dark:#F97583;--shiki-dark-font-style:inherit;--shiki-default:#D73A49;--shiki-default-font-style:inherit;--shiki-sepia:#66D9EF;--shiki-sepia-font-style:italic"},"children":[{"type":"text","value":" void"}]},{"type":"element","tag":"span","props":{"style":"--shiki-dark:#B392F0;--shiki-default:#6F42C1;--shiki-sepia:#A6E22E"},"children":[{"type":"text","value":" onChanged"}]},{"type":"element","tag":"span","props":{"style":"--shiki-dark:#E1E4E8;--shiki-default:#24292E;--shiki-sepia:#F8F8F2"},"children":[{"type":"text","value":"(@"}]},{"type":"element","tag":"span","props":{"style":"--shiki-dark:#F97583;--shiki-dark-font-style:inherit;--shiki-default:#D73A49;--shiki-default-font-style:inherit;--shiki-sepia:#66D9EF;--shiki-sepia-font-style:italic"},"children":[{"type":"text","value":"Nullable"}]},{"type":"element","tag":"span","props":{"style":"--shiki-dark:#E1E4E8;--shiki-dark-font-style:inherit;--shiki-default:#24292E;--shiki-default-font-style:inherit;--shiki-sepia:#66D9EF;--shiki-sepia-font-style:italic"},"children":[{"type":"text","value":" List"}]},{"type":"element","tag":"span","props":{"style":"--shiki-dark:#E1E4E8;--shiki-default:#24292E;--shiki-sepia:#F8F8F2"},"children":[{"type":"text","value":"<"}]},{"type":"element","tag":"span","props":{"style":"--shiki-dark:#F97583;--shiki-dark-font-style:inherit;--shiki-default:#D73A49;--shiki-default-font-style:inherit;--shiki-sepia:#66D9EF;--shiki-sepia-font-style:italic"},"children":[{"type":"text","value":"Employee"}]},{"type":"element","tag":"span","props":{"style":"--shiki-dark:#E1E4E8;--shiki-default:#24292E;--shiki-sepia:#F8F8F2"},"children":[{"type":"text","value":"> "}]},{"type":"element","tag":"span","props":{"style":"--shiki-dark:#FFAB70;--shiki-dark-font-style:inherit;--shiki-default:#E36209;--shiki-default-font-style:inherit;--shiki-sepia:#FD971F;--shiki-sepia-font-style:italic"},"children":[{"type":"text","value":"employees"}]},{"type":"element","tag":"span","props":{"style":"--shiki-dark:#E1E4E8;--shiki-default:#24292E;--shiki-sepia:#F8F8F2"},"children":[{"type":"text","value":") {\n"}]}]},{"type":"element","tag":"span","props":{"class":"line","line":6},"children":[{"type":"element","tag":"span","props":{"style":"--shiki-dark:#B392F0;--shiki-default:#6F42C1;--shiki-sepia:#A6E22E"},"children":[{"type":"text","value":"       log"}]},{"type":"element","tag":"span","props":{"style":"--shiki-dark:#E1E4E8;--shiki-default:#24292E;--shiki-sepia:#F8F8F2"},"children":[{"type":"text","value":"("}]},{"type":"element","tag":"span","props":{"style":"--shiki-dark:#9ECBFF;--shiki-default:#032F62;--shiki-sepia:#E6DB74"},"children":[{"type":"text","value":"\"onChanged \""}]},{"type":"element","tag":"span","props":{"style":"--shiki-dark:#F97583;--shiki-default:#D73A49;--shiki-sepia:#F92672"},"children":[{"type":"text","value":" +"}]},{"type":"element","tag":"span","props":{"style":"--shiki-dark:#E1E4E8;--shiki-default:#24292E;--shiki-sepia:#F8F8F2"},"children":[{"type":"text","value":" employees);\n"}]}]},{"type":"element","tag":"span","props":{"class":"line","line":7},"children":[{"type":"element","tag":"span","props":{"style":"--shiki-dark:#E1E4E8;--shiki-default:#24292E;--shiki-sepia:#F8F8F2"},"children":[{"type":"text","value":"   }\n"}]}]},{"type":"element","tag":"span","props":{"class":"line","line":8},"children":[{"type":"element","tag":"span","props":{"style":"--shiki-dark:#E1E4E8;--shiki-default:#24292E;--shiki-sepia:#F8F8F2"},"children":[{"type":"text","value":"});\n"}]}]}]}]},{"type":"element","tag":"p","props":{},"children":[{"type":"text","value":"Отримуємо "},{"type":"element","tag":"code","props":{"className":[]},"children":[{"type":"text","value":"LiveData"}]},{"type":"text","value":" і підписуємося на нього."}]},{"type":"element","tag":"p","props":{},"children":[{"type":"text","value":"Використання "},{"type":"element","tag":"code","props":{"className":[]},"children":[{"type":"text","value":"LiveData"}]},{"type":"text","value":" має величезну перевагу перед використанням списку або масиву. Підписавшись на "},{"type":"element","tag":"code","props":{"className":[]},"children":[{"type":"text","value":"LiveData"}]},{"type":"text","value":", ви отримуватимете свіжі дані під час їхньої зміни в базі. Тобто при додаванні нових, видаленні старих або оновленні поточних даних у таблиці "},{"type":"element","tag":"code","props":{"className":[]},"children":[{"type":"text","value":"employee"}]},{"type":"text","value":", Room знову виконає ваш "},{"type":"element","tag":"code","props":{"className":[]},"children":[{"type":"text","value":"Query"}]},{"type":"text","value":" запит, і ви отримаєте в "},{"type":"element","tag":"code","props":{"className":[]},"children":[{"type":"text","value":"onChanged"}]},{"type":"text","value":" методі актуальні дані з урахуванням останніх змін. Вам більше не треба самим запитувати ці дані щоразу. І все це буде приходити вам в UI потік."}]},{"type":"element","tag":"h2","props":{"id":"передача-параметрів"},"children":[{"type":"text","value":"Передача параметрів"}]},{"type":"element","tag":"p","props":{},"children":[{"type":"text","value":"У "},{"type":"element","tag":"code","props":{"className":[]},"children":[{"type":"text","value":"Query"}]},{"type":"text","value":" можна передавати параметри, щоб зробити запити більш конкретними.\nНаприклад, запит даних за "},{"type":"element","tag":"code","props":{"className":[]},"children":[{"type":"text","value":"id"}]}]},{"type":"element","tag":"pre","props":{"className":"language-java shiki shiki-themes github-dark github-light monokai","code":"@Query(\"SELECT * FROM employee WHERE id = :employeeId\")\nEmployee getById(long employeeId);\n","language":"java","meta":"","style":""},"children":[{"type":"element","tag":"code","props":{"__ignoreMap":""},"children":[{"type":"element","tag":"span","props":{"class":"line","line":1},"children":[{"type":"element","tag":"span","props":{"style":"--shiki-dark:#E1E4E8;--shiki-default:#24292E;--shiki-sepia:#F8F8F2"},"children":[{"type":"text","value":"@"}]},{"type":"element","tag":"span","props":{"style":"--shiki-dark:#F97583;--shiki-dark-font-style:inherit;--shiki-default:#D73A49;--shiki-default-font-style:inherit;--shiki-sepia:#66D9EF;--shiki-sepia-font-style:italic"},"children":[{"type":"text","value":"Query"}]},{"type":"element","tag":"span","props":{"style":"--shiki-dark:#E1E4E8;--shiki-default:#24292E;--shiki-sepia:#F8F8F2"},"children":[{"type":"text","value":"("}]},{"type":"element","tag":"span","props":{"style":"--shiki-dark:#9ECBFF;--shiki-default:#032F62;--shiki-sepia:#E6DB74"},"children":[{"type":"text","value":"\"SELECT * FROM employee WHERE id = :employeeId\""}]},{"type":"element","tag":"span","props":{"style":"--shiki-dark:#E1E4E8;--shiki-default:#24292E;--shiki-sepia:#F8F8F2"},"children":[{"type":"text","value":")\n"}]}]},{"type":"element","tag":"span","props":{"class":"line","line":2},"children":[{"type":"element","tag":"span","props":{"style":"--shiki-dark:#E1E4E8;--shiki-dark-font-style:inherit;--shiki-default:#24292E;--shiki-default-font-style:inherit;--shiki-sepia:#66D9EF;--shiki-sepia-font-style:italic"},"children":[{"type":"text","value":"Employee"}]},{"type":"element","tag":"span","props":{"style":"--shiki-dark:#B392F0;--shiki-default:#6F42C1;--shiki-sepia:#A6E22E"},"children":[{"type":"text","value":" getById"}]},{"type":"element","tag":"span","props":{"style":"--shiki-dark:#E1E4E8;--shiki-default:#24292E;--shiki-sepia:#F8F8F2"},"children":[{"type":"text","value":"("}]},{"type":"element","tag":"span","props":{"style":"--shiki-dark:#F97583;--shiki-dark-font-style:inherit;--shiki-default:#D73A49;--shiki-default-font-style:inherit;--shiki-sepia:#66D9EF;--shiki-sepia-font-style:italic"},"children":[{"type":"text","value":"long"}]},{"type":"element","tag":"span","props":{"style":"--shiki-dark:#E1E4E8;--shiki-default:#24292E;--shiki-sepia:#F8F8F2"},"children":[{"type":"text","value":" employeeId);\n"}]}]}]}]},{"type":"element","tag":"p","props":{},"children":[{"type":"text","value":"Перед параметром "},{"type":"element","tag":"code","props":{"className":[]},"children":[{"type":"text","value":"employeeId"}]},{"type":"text","value":" у запиті має стояти двокрапка. Room візьме значення цього параметра з методу і підставить його в запит."}]},{"type":"element","tag":"p","props":{},"children":[{"type":"text","value":"Розглянемо ще кілька прикладів:"}]},{"type":"element","tag":"p","props":{},"children":[{"type":"text","value":"Пошук співробітників із зарплатою, більшою за задане значення"}]},{"type":"element","tag":"pre","props":{"className":"language-java shiki shiki-themes github-dark github-light monokai","code":"@Query(\"SELECT * FROM employee WHERE salary > :minSalary\")\nList<Employee> getAllWithSalaryMoreThan(int minSalary);\n","language":"java","meta":"","style":""},"children":[{"type":"element","tag":"code","props":{"__ignoreMap":""},"children":[{"type":"element","tag":"span","props":{"class":"line","line":1},"children":[{"type":"element","tag":"span","props":{"style":"--shiki-dark:#E1E4E8;--shiki-default:#24292E;--shiki-sepia:#F8F8F2"},"children":[{"type":"text","value":"@"}]},{"type":"element","tag":"span","props":{"style":"--shiki-dark:#F97583;--shiki-dark-font-style:inherit;--shiki-default:#D73A49;--shiki-default-font-style:inherit;--shiki-sepia:#66D9EF;--shiki-sepia-font-style:italic"},"children":[{"type":"text","value":"Query"}]},{"type":"element","tag":"span","props":{"style":"--shiki-dark:#E1E4E8;--shiki-default:#24292E;--shiki-sepia:#F8F8F2"},"children":[{"type":"text","value":"("}]},{"type":"element","tag":"span","props":{"style":"--shiki-dark:#9ECBFF;--shiki-default:#032F62;--shiki-sepia:#E6DB74"},"children":[{"type":"text","value":"\"SELECT * FROM employee WHERE salary > :minSalary\""}]},{"type":"element","tag":"span","props":{"style":"--shiki-dark:#E1E4E8;--shiki-default:#24292E;--shiki-sepia:#F8F8F2"},"children":[{"type":"text","value":")\n"}]}]},{"type":"element","tag":"span","props":{"class":"line","line":2},"children":[{"type":"element","tag":"span","props":{"style":"--shiki-dark:#E1E4E8;--shiki-dark-font-style:inherit;--shiki-default:#24292E;--shiki-default-font-style:inherit;--shiki-sepia:#66D9EF;--shiki-sepia-font-style:italic"},"children":[{"type":"text","value":"List"}]},{"type":"element","tag":"span","props":{"style":"--shiki-dark:#F97583;--shiki-default:#D73A49;--shiki-sepia:#F92672"},"children":[{"type":"text","value":"<"}]},{"type":"element","tag":"span","props":{"style":"--shiki-dark:#E1E4E8;--shiki-default:#24292E;--shiki-sepia:#F8F8F2"},"children":[{"type":"text","value":"Employee"}]},{"type":"element","tag":"span","props":{"style":"--shiki-dark:#F97583;--shiki-default:#D73A49;--shiki-sepia:#F92672"},"children":[{"type":"text","value":">"}]},{"type":"element","tag":"span","props":{"style":"--shiki-dark:#B392F0;--shiki-default:#6F42C1;--shiki-sepia:#A6E22E"},"children":[{"type":"text","value":" getAllWithSalaryMoreThan"}]},{"type":"element","tag":"span","props":{"style":"--shiki-dark:#E1E4E8;--shiki-default:#24292E;--shiki-sepia:#F8F8F2"},"children":[{"type":"text","value":"("}]},{"type":"element","tag":"span","props":{"style":"--shiki-dark:#F97583;--shiki-dark-font-style:inherit;--shiki-default:#D73A49;--shiki-default-font-style:inherit;--shiki-sepia:#66D9EF;--shiki-sepia-font-style:italic"},"children":[{"type":"text","value":"int"}]},{"type":"element","tag":"span","props":{"style":"--shiki-dark:#E1E4E8;--shiki-default:#24292E;--shiki-sepia:#F8F8F2"},"children":[{"type":"text","value":" minSalary);\n"}]}]}]}]},{"type":"element","tag":"p","props":{},"children":[{"type":"text","value":"Пошук співробітників із зарплатою в заданому діапазоні"}]},{"type":"element","tag":"pre","props":{"className":"language-java shiki shiki-themes github-dark github-light monokai","code":"@Query(\"SELECT * FROM employee WHERE salary BETWEEN :minSalary AND :maxSalary\")\nList<Employee> getAllWithSalaryBetween(int minSalary, int maxSalary);\n","language":"java","meta":"","style":""},"children":[{"type":"element","tag":"code","props":{"__ignoreMap":""},"children":[{"type":"element","tag":"span","props":{"class":"line","line":1},"children":[{"type":"element","tag":"span","props":{"style":"--shiki-dark:#E1E4E8;--shiki-default:#24292E;--shiki-sepia:#F8F8F2"},"children":[{"type":"text","value":"@"}]},{"type":"element","tag":"span","props":{"style":"--shiki-dark:#F97583;--shiki-dark-font-style:inherit;--shiki-default:#D73A49;--shiki-default-font-style:inherit;--shiki-sepia:#66D9EF;--shiki-sepia-font-style:italic"},"children":[{"type":"text","value":"Query"}]},{"type":"element","tag":"span","props":{"style":"--shiki-dark:#E1E4E8;--shiki-default:#24292E;--shiki-sepia:#F8F8F2"},"children":[{"type":"text","value":"("}]},{"type":"element","tag":"span","props":{"style":"--shiki-dark:#9ECBFF;--shiki-default:#032F62;--shiki-sepia:#E6DB74"},"children":[{"type":"text","value":"\"SELECT * FROM employee WHERE salary BETWEEN :minSalary AND :maxSalary\""}]},{"type":"element","tag":"span","props":{"style":"--shiki-dark:#E1E4E8;--shiki-default:#24292E;--shiki-sepia:#F8F8F2"},"children":[{"type":"text","value":")\n"}]}]},{"type":"element","tag":"span","props":{"class":"line","line":2},"children":[{"type":"element","tag":"span","props":{"style":"--shiki-dark:#E1E4E8;--shiki-dark-font-style:inherit;--shiki-default:#24292E;--shiki-default-font-style:inherit;--shiki-sepia:#66D9EF;--shiki-sepia-font-style:italic"},"children":[{"type":"text","value":"List"}]},{"type":"element","tag":"span","props":{"style":"--shiki-dark:#F97583;--shiki-default:#D73A49;--shiki-sepia:#F92672"},"children":[{"type":"text","value":"<"}]},{"type":"element","tag":"span","props":{"style":"--shiki-dark:#E1E4E8;--shiki-default:#24292E;--shiki-sepia:#F8F8F2"},"children":[{"type":"text","value":"Employee"}]},{"type":"element","tag":"span","props":{"style":"--shiki-dark:#F97583;--shiki-default:#D73A49;--shiki-sepia:#F92672"},"children":[{"type":"text","value":">"}]},{"type":"element","tag":"span","props":{"style":"--shiki-dark:#B392F0;--shiki-default:#6F42C1;--shiki-sepia:#A6E22E"},"children":[{"type":"text","value":" getAllWithSalaryBetween"}]},{"type":"element","tag":"span","props":{"style":"--shiki-dark:#E1E4E8;--shiki-default:#24292E;--shiki-sepia:#F8F8F2"},"children":[{"type":"text","value":"("}]},{"type":"element","tag":"span","props":{"style":"--shiki-dark:#F97583;--shiki-dark-font-style:inherit;--shiki-default:#D73A49;--shiki-default-font-style:inherit;--shiki-sepia:#66D9EF;--shiki-sepia-font-style:italic"},"children":[{"type":"text","value":"int"}]},{"type":"element","tag":"span","props":{"style":"--shiki-dark:#E1E4E8;--shiki-default:#24292E;--shiki-sepia:#F8F8F2"},"children":[{"type":"text","value":" minSalary, "}]},{"type":"element","tag":"span","props":{"style":"--shiki-dark:#F97583;--shiki-dark-font-style:inherit;--shiki-default:#D73A49;--shiki-default-font-style:inherit;--shiki-sepia:#66D9EF;--shiki-sepia-font-style:italic"},"children":[{"type":"text","value":"int"}]},{"type":"element","tag":"span","props":{"style":"--shiki-dark:#E1E4E8;--shiki-default:#24292E;--shiki-sepia:#F8F8F2"},"children":[{"type":"text","value":" maxSalary);\n"}]}]}]}]},{"type":"element","tag":"p","props":{},"children":[{"type":"text","value":"Пошук співробітників за ім'ям або прізвищем"}]},{"type":"element","tag":"pre","props":{"className":"language-java shiki shiki-themes github-dark github-light monokai","code":"@Query(\"SELECT * FROM employee WHERE first_name LIKE :search OR last_name LIKE :search\")\nList<Employee> getAllWithNameLike(String search);\n","language":"java","meta":"","style":""},"children":[{"type":"element","tag":"code","props":{"__ignoreMap":""},"children":[{"type":"element","tag":"span","props":{"class":"line","line":1},"children":[{"type":"element","tag":"span","props":{"style":"--shiki-dark:#E1E4E8;--shiki-default:#24292E;--shiki-sepia:#F8F8F2"},"children":[{"type":"text","value":"@"}]},{"type":"element","tag":"span","props":{"style":"--shiki-dark:#F97583;--shiki-dark-font-style:inherit;--shiki-default:#D73A49;--shiki-default-font-style:inherit;--shiki-sepia:#66D9EF;--shiki-sepia-font-style:italic"},"children":[{"type":"text","value":"Query"}]},{"type":"element","tag":"span","props":{"style":"--shiki-dark:#E1E4E8;--shiki-default:#24292E;--shiki-sepia:#F8F8F2"},"children":[{"type":"text","value":"("}]},{"type":"element","tag":"span","props":{"style":"--shiki-dark:#9ECBFF;--shiki-default:#032F62;--shiki-sepia:#E6DB74"},"children":[{"type":"text","value":"\"SELECT * FROM employee WHERE first_name LIKE :search OR last_name LIKE :search\""}]},{"type":"element","tag":"span","props":{"style":"--shiki-dark:#E1E4E8;--shiki-default:#24292E;--shiki-sepia:#F8F8F2"},"children":[{"type":"text","value":")\n"}]}]},{"type":"element","tag":"span","props":{"class":"line","line":2},"children":[{"type":"element","tag":"span","props":{"style":"--shiki-dark:#E1E4E8;--shiki-dark-font-style:inherit;--shiki-default:#24292E;--shiki-default-font-style:inherit;--shiki-sepia:#66D9EF;--shiki-sepia-font-style:italic"},"children":[{"type":"text","value":"List"}]},{"type":"element","tag":"span","props":{"style":"--shiki-dark:#F97583;--shiki-default:#D73A49;--shiki-sepia:#F92672"},"children":[{"type":"text","value":"<"}]},{"type":"element","tag":"span","props":{"style":"--shiki-dark:#E1E4E8;--shiki-default:#24292E;--shiki-sepia:#F8F8F2"},"children":[{"type":"text","value":"Employee"}]},{"type":"element","tag":"span","props":{"style":"--shiki-dark:#F97583;--shiki-default:#D73A49;--shiki-sepia:#F92672"},"children":[{"type":"text","value":">"}]},{"type":"element","tag":"span","props":{"style":"--shiki-dark:#B392F0;--shiki-default:#6F42C1;--shiki-sepia:#A6E22E"},"children":[{"type":"text","value":" getAllWithNameLike"}]},{"type":"element","tag":"span","props":{"style":"--shiki-dark:#E1E4E8;--shiki-default:#24292E;--shiki-sepia:#F8F8F2"},"children":[{"type":"text","value":"("}]},{"type":"element","tag":"span","props":{"style":"--shiki-dark:#E1E4E8;--shiki-dark-font-style:inherit;--shiki-default:#24292E;--shiki-default-font-style:inherit;--shiki-sepia:#66D9EF;--shiki-sepia-font-style:italic"},"children":[{"type":"text","value":"String"}]},{"type":"element","tag":"span","props":{"style":"--shiki-dark:#E1E4E8;--shiki-default:#24292E;--shiki-sepia:#F8F8F2"},"children":[{"type":"text","value":" search);\n"}]}]}]}]},{"type":"element","tag":"p","props":{},"children":[{"type":"text","value":"Пошук співробітників за списком id."}]},{"type":"element","tag":"pre","props":{"className":"language-java shiki shiki-themes github-dark github-light monokai","code":"@Query(\"SELECT * FROM employee WHERE id IN (:idList)\")\nList<Employee> getByIdList(List<Long> idList);\n","language":"java","meta":"","style":""},"children":[{"type":"element","tag":"code","props":{"__ignoreMap":""},"children":[{"type":"element","tag":"span","props":{"class":"line","line":1},"children":[{"type":"element","tag":"span","props":{"style":"--shiki-dark:#E1E4E8;--shiki-default:#24292E;--shiki-sepia:#F8F8F2"},"children":[{"type":"text","value":"@"}]},{"type":"element","tag":"span","props":{"style":"--shiki-dark:#F97583;--shiki-dark-font-style:inherit;--shiki-default:#D73A49;--shiki-default-font-style:inherit;--shiki-sepia:#66D9EF;--shiki-sepia-font-style:italic"},"children":[{"type":"text","value":"Query"}]},{"type":"element","tag":"span","props":{"style":"--shiki-dark:#E1E4E8;--shiki-default:#24292E;--shiki-sepia:#F8F8F2"},"children":[{"type":"text","value":"("}]},{"type":"element","tag":"span","props":{"style":"--shiki-dark:#9ECBFF;--shiki-default:#032F62;--shiki-sepia:#E6DB74"},"children":[{"type":"text","value":"\"SELECT * FROM employee WHERE id IN (:idList)\""}]},{"type":"element","tag":"span","props":{"style":"--shiki-dark:#E1E4E8;--shiki-default:#24292E;--shiki-sepia:#F8F8F2"},"children":[{"type":"text","value":")\n"}]}]},{"type":"element","tag":"span","props":{"class":"line","line":2},"children":[{"type":"element","tag":"span","props":{"style":"--shiki-dark:#E1E4E8;--shiki-dark-font-style:inherit;--shiki-default:#24292E;--shiki-default-font-style:inherit;--shiki-sepia:#66D9EF;--shiki-sepia-font-style:italic"},"children":[{"type":"text","value":"List"}]},{"type":"element","tag":"span","props":{"style":"--shiki-dark:#F97583;--shiki-default:#D73A49;--shiki-sepia:#F92672"},"children":[{"type":"text","value":"<"}]},{"type":"element","tag":"span","props":{"style":"--shiki-dark:#E1E4E8;--shiki-default:#24292E;--shiki-sepia:#F8F8F2"},"children":[{"type":"text","value":"Employee"}]},{"type":"element","tag":"span","props":{"style":"--shiki-dark:#F97583;--shiki-default:#D73A49;--shiki-sepia:#F92672"},"children":[{"type":"text","value":">"}]},{"type":"element","tag":"span","props":{"style":"--shiki-dark:#B392F0;--shiki-default:#6F42C1;--shiki-sepia:#A6E22E"},"children":[{"type":"text","value":" getByIdList"}]},{"type":"element","tag":"span","props":{"style":"--shiki-dark:#E1E4E8;--shiki-default:#24292E;--shiki-sepia:#F8F8F2"},"children":[{"type":"text","value":"("}]},{"type":"element","tag":"span","props":{"style":"--shiki-dark:#E1E4E8;--shiki-dark-font-style:inherit;--shiki-default:#24292E;--shiki-default-font-style:inherit;--shiki-sepia:#66D9EF;--shiki-sepia-font-style:italic"},"children":[{"type":"text","value":"List"}]},{"type":"element","tag":"span","props":{"style":"--shiki-dark:#F97583;--shiki-default:#D73A49;--shiki-sepia:#F92672"},"children":[{"type":"text","value":"<"}]},{"type":"element","tag":"span","props":{"style":"--shiki-dark:#E1E4E8;--shiki-default:#24292E;--shiki-sepia:#F8F8F2"},"children":[{"type":"text","value":"Long"}]},{"type":"element","tag":"span","props":{"style":"--shiki-dark:#F97583;--shiki-default:#D73A49;--shiki-sepia:#F92672"},"children":[{"type":"text","value":">"}]},{"type":"element","tag":"span","props":{"style":"--shiki-dark:#E1E4E8;--shiki-default:#24292E;--shiki-sepia:#F8F8F2"},"children":[{"type":"text","value":" idList);\n"}]}]}]}]},{"type":"element","tag":"h2","props":{"id":"subsets"},"children":[{"type":"text","value":"Subsets"}]},{"type":"element","tag":"p","props":{},"children":[{"type":"text","value":"Часто під час запиту даних нам потрібно отримати з таблиці не всі поля, а тільки деякі. Такі запити швидше і легше, ніж тягнути всі поля."}]},{"type":"element","tag":"p","props":{},"children":[{"type":"text","value":"Припустимо, нам треба отримувати тільки ім'я та прізвище співробітника. Якщо зробити так:"}]},{"type":"element","tag":"pre","props":{"className":"language-java shiki shiki-themes github-dark github-light monokai","code":"@Query(\"SELECT first_name, last_name FROM employee\")\nList<Employee> getNames();\n","language":"java","meta":"","style":""},"children":[{"type":"element","tag":"code","props":{"__ignoreMap":""},"children":[{"type":"element","tag":"span","props":{"class":"line","line":1},"children":[{"type":"element","tag":"span","props":{"style":"--shiki-dark:#E1E4E8;--shiki-default:#24292E;--shiki-sepia:#F8F8F2"},"children":[{"type":"text","value":"@"}]},{"type":"element","tag":"span","props":{"style":"--shiki-dark:#F97583;--shiki-dark-font-style:inherit;--shiki-default:#D73A49;--shiki-default-font-style:inherit;--shiki-sepia:#66D9EF;--shiki-sepia-font-style:italic"},"children":[{"type":"text","value":"Query"}]},{"type":"element","tag":"span","props":{"style":"--shiki-dark:#E1E4E8;--shiki-default:#24292E;--shiki-sepia:#F8F8F2"},"children":[{"type":"text","value":"("}]},{"type":"element","tag":"span","props":{"style":"--shiki-dark:#9ECBFF;--shiki-default:#032F62;--shiki-sepia:#E6DB74"},"children":[{"type":"text","value":"\"SELECT first_name, last_name FROM employee\""}]},{"type":"element","tag":"span","props":{"style":"--shiki-dark:#E1E4E8;--shiki-default:#24292E;--shiki-sepia:#F8F8F2"},"children":[{"type":"text","value":")\n"}]}]},{"type":"element","tag":"span","props":{"class":"line","line":2},"children":[{"type":"element","tag":"span","props":{"style":"--shiki-dark:#E1E4E8;--shiki-dark-font-style:inherit;--shiki-default:#24292E;--shiki-default-font-style:inherit;--shiki-sepia:#66D9EF;--shiki-sepia-font-style:italic"},"children":[{"type":"text","value":"List"}]},{"type":"element","tag":"span","props":{"style":"--shiki-dark:#F97583;--shiki-default:#D73A49;--shiki-sepia:#F92672"},"children":[{"type":"text","value":"<"}]},{"type":"element","tag":"span","props":{"style":"--shiki-dark:#E1E4E8;--shiki-default:#24292E;--shiki-sepia:#F8F8F2"},"children":[{"type":"text","value":"Employee"}]},{"type":"element","tag":"span","props":{"style":"--shiki-dark:#F97583;--shiki-default:#D73A49;--shiki-sepia:#F92672"},"children":[{"type":"text","value":">"}]},{"type":"element","tag":"span","props":{"style":"--shiki-dark:#B392F0;--shiki-default:#6F42C1;--shiki-sepia:#A6E22E"},"children":[{"type":"text","value":" getNames"}]},{"type":"element","tag":"span","props":{"style":"--shiki-dark:#E1E4E8;--shiki-default:#24292E;--shiki-sepia:#F8F8F2"},"children":[{"type":"text","value":"();\n"}]}]}]}]},{"type":"element","tag":"p","props":{},"children":[{"type":"text","value":"то вже під час компіляції отримаємо помилку: "},{"type":"element","tag":"code","props":{"className":[]},"children":[{"type":"text","value":"The columns returned by the query does not have the fields [id,salary] in Employee even though they are annotated as non-null or primitive"}]},{"type":"text","value":". Стовпці, повернуті запитом: "},{"type":"element","tag":"span","props":{},"children":[{"type":"text","value":"first_name, last_name"}]},{"type":"text","value":"."}]},{"type":"element","tag":"p","props":{},"children":[{"type":"text","value":"Room повідомляє, що в даних, які поверне цей запит, не вистачає полів, щоб заповнити всі поля об'єкта "},{"type":"element","tag":"code","props":{"className":[]},"children":[{"type":"text","value":"Employee"}]},{"type":"text","value":"."}]},{"type":"element","tag":"p","props":{},"children":[{"type":"text","value":"У цьому випадку ми можемо використовувати окремий об'єкт."}]},{"type":"element","tag":"pre","props":{"className":"language-java shiki shiki-themes github-dark github-light monokai","code":"public class Name {\n \n   @ColumnInfo(name = \"first_name\")\n   public String firstName;\n \n   @ColumnInfo(name = \"last_name\")\n   public String lastName;\n \n}\n","language":"java","meta":"","style":""},"children":[{"type":"element","tag":"code","props":{"__ignoreMap":""},"children":[{"type":"element","tag":"span","props":{"class":"line","line":1},"children":[{"type":"element","tag":"span","props":{"style":"--shiki-dark:#F97583;--shiki-default:#D73A49;--shiki-sepia:#F92672"},"children":[{"type":"text","value":"public"}]},{"type":"element","tag":"span","props":{"style":"--shiki-dark:#F97583;--shiki-default:#D73A49;--shiki-sepia:#F92672"},"children":[{"type":"text","value":" class"}]},{"type":"element","tag":"span","props":{"style":"--shiki-dark:#B392F0;--shiki-dark-text-decoration:inherit;--shiki-default:#6F42C1;--shiki-default-text-decoration:inherit;--shiki-sepia:#A6E22E;--shiki-sepia-text-decoration:underline"},"children":[{"type":"text","value":" Name"}]},{"type":"element","tag":"span","props":{"style":"--shiki-dark:#E1E4E8;--shiki-default:#24292E;--shiki-sepia:#F8F8F2"},"children":[{"type":"text","value":" {\n"}]}]},{"type":"element","tag":"span","props":{"class":"line","line":2},"children":[{"type":"element","tag":"span","props":{"style":"--shiki-dark:#E1E4E8;--shiki-default:#24292E;--shiki-sepia:#F8F8F2"},"children":[{"type":"text","value":" \n"}]}]},{"type":"element","tag":"span","props":{"class":"line","line":3},"children":[{"type":"element","tag":"span","props":{"style":"--shiki-dark:#E1E4E8;--shiki-default:#24292E;--shiki-sepia:#F8F8F2"},"children":[{"type":"text","value":"   @"}]},{"type":"element","tag":"span","props":{"style":"--shiki-dark:#F97583;--shiki-dark-font-style:inherit;--shiki-default:#D73A49;--shiki-default-font-style:inherit;--shiki-sepia:#66D9EF;--shiki-sepia-font-style:italic"},"children":[{"type":"text","value":"ColumnInfo"}]},{"type":"element","tag":"span","props":{"style":"--shiki-dark:#E1E4E8;--shiki-default:#24292E;--shiki-sepia:#F8F8F2"},"children":[{"type":"text","value":"("}]},{"type":"element","tag":"span","props":{"style":"--shiki-dark:#79B8FF;--shiki-default:#005CC5;--shiki-sepia:#AE81FF"},"children":[{"type":"text","value":"name"}]},{"type":"element","tag":"span","props":{"style":"--shiki-dark:#F97583;--shiki-default:#D73A49;--shiki-sepia:#F92672"},"children":[{"type":"text","value":" ="}]},{"type":"element","tag":"span","props":{"style":"--shiki-dark:#9ECBFF;--shiki-default:#032F62;--shiki-sepia:#E6DB74"},"children":[{"type":"text","value":" \"first_name\""}]},{"type":"element","tag":"span","props":{"style":"--shiki-dark:#E1E4E8;--shiki-default:#24292E;--shiki-sepia:#F8F8F2"},"children":[{"type":"text","value":")\n"}]}]},{"type":"element","tag":"span","props":{"class":"line","line":4},"children":[{"type":"element","tag":"span","props":{"style":"--shiki-dark:#F97583;--shiki-default:#D73A49;--shiki-sepia:#F92672"},"children":[{"type":"text","value":"   public"}]},{"type":"element","tag":"span","props":{"style":"--shiki-dark:#E1E4E8;--shiki-dark-font-style:inherit;--shiki-default:#24292E;--shiki-default-font-style:inherit;--shiki-sepia:#66D9EF;--shiki-sepia-font-style:italic"},"children":[{"type":"text","value":" String"}]},{"type":"element","tag":"span","props":{"style":"--shiki-dark:#E1E4E8;--shiki-default:#24292E;--shiki-sepia:#F8F8F2"},"children":[{"type":"text","value":" firstName;\n"}]}]},{"type":"element","tag":"span","props":{"class":"line","line":5},"children":[{"type":"element","tag":"span","props":{"style":"--shiki-dark:#E1E4E8;--shiki-default:#24292E;--shiki-sepia:#F8F8F2"},"children":[{"type":"text","value":" \n"}]}]},{"type":"element","tag":"span","props":{"class":"line","line":6},"children":[{"type":"element","tag":"span","props":{"style":"--shiki-dark:#E1E4E8;--shiki-default:#24292E;--shiki-sepia:#F8F8F2"},"children":[{"type":"text","value":"   @"}]},{"type":"element","tag":"span","props":{"style":"--shiki-dark:#F97583;--shiki-dark-font-style:inherit;--shiki-default:#D73A49;--shiki-default-font-style:inherit;--shiki-sepia:#66D9EF;--shiki-sepia-font-style:italic"},"children":[{"type":"text","value":"ColumnInfo"}]},{"type":"element","tag":"span","props":{"style":"--shiki-dark:#E1E4E8;--shiki-default:#24292E;--shiki-sepia:#F8F8F2"},"children":[{"type":"text","value":"("}]},{"type":"element","tag":"span","props":{"style":"--shiki-dark:#79B8FF;--shiki-default:#005CC5;--shiki-sepia:#AE81FF"},"children":[{"type":"text","value":"name"}]},{"type":"element","tag":"span","props":{"style":"--shiki-dark:#F97583;--shiki-default:#D73A49;--shiki-sepia:#F92672"},"children":[{"type":"text","value":" ="}]},{"type":"element","tag":"span","props":{"style":"--shiki-dark:#9ECBFF;--shiki-default:#032F62;--shiki-sepia:#E6DB74"},"children":[{"type":"text","value":" \"last_name\""}]},{"type":"element","tag":"span","props":{"style":"--shiki-dark:#E1E4E8;--shiki-default:#24292E;--shiki-sepia:#F8F8F2"},"children":[{"type":"text","value":")\n"}]}]},{"type":"element","tag":"span","props":{"class":"line","line":7},"children":[{"type":"element","tag":"span","props":{"style":"--shiki-dark:#F97583;--shiki-default:#D73A49;--shiki-sepia:#F92672"},"children":[{"type":"text","value":"   public"}]},{"type":"element","tag":"span","props":{"style":"--shiki-dark:#E1E4E8;--shiki-dark-font-style:inherit;--shiki-default:#24292E;--shiki-default-font-style:inherit;--shiki-sepia:#66D9EF;--shiki-sepia-font-style:italic"},"children":[{"type":"text","value":" String"}]},{"type":"element","tag":"span","props":{"style":"--shiki-dark:#E1E4E8;--shiki-default:#24292E;--shiki-sepia:#F8F8F2"},"children":[{"type":"text","value":" lastName;\n"}]}]},{"type":"element","tag":"span","props":{"class":"line","line":8},"children":[{"type":"element","tag":"span","props":{"style":"--shiki-dark:#E1E4E8;--shiki-default:#24292E;--shiki-sepia:#F8F8F2"},"children":[{"type":"text","value":" \n"}]}]},{"type":"element","tag":"span","props":{"class":"line","line":9},"children":[{"type":"element","tag":"span","props":{"style":"--shiki-dark:#E1E4E8;--shiki-default:#24292E;--shiki-sepia:#F8F8F2"},"children":[{"type":"text","value":"}\n"}]}]}]}]},{"type":"element","tag":"p","props":{},"children":[{"type":"text","value":"Зверніть увагу, що він не "},{"type":"element","tag":"code","props":{"className":[]},"children":[{"type":"text","value":"Entity"}]},{"type":"text","value":". Це звичайний клас. За допомогою "},{"type":"element","tag":"code","props":{"className":[]},"children":[{"type":"text","value":"ColumnInfo"}]},{"type":"text","value":" ми налаштовуємо імена полів, щоб вони збігалися з полями таблиці."}]},{"type":"element","tag":"p","props":{},"children":[{"type":"text","value":"Використовуємо цей клас у методі запиту:"}]},{"type":"element","tag":"pre","props":{"className":"language-java shiki shiki-themes github-dark github-light monokai","code":"@Query(\"SELECT first_name, last_name FROM employee\")\nList<Name> getNames();\n","language":"java","meta":"","style":""},"children":[{"type":"element","tag":"code","props":{"__ignoreMap":""},"children":[{"type":"element","tag":"span","props":{"class":"line","line":1},"children":[{"type":"element","tag":"span","props":{"style":"--shiki-dark:#E1E4E8;--shiki-default:#24292E;--shiki-sepia:#F8F8F2"},"children":[{"type":"text","value":"@"}]},{"type":"element","tag":"span","props":{"style":"--shiki-dark:#F97583;--shiki-dark-font-style:inherit;--shiki-default:#D73A49;--shiki-default-font-style:inherit;--shiki-sepia:#66D9EF;--shiki-sepia-font-style:italic"},"children":[{"type":"text","value":"Query"}]},{"type":"element","tag":"span","props":{"style":"--shiki-dark:#E1E4E8;--shiki-default:#24292E;--shiki-sepia:#F8F8F2"},"children":[{"type":"text","value":"("}]},{"type":"element","tag":"span","props":{"style":"--shiki-dark:#9ECBFF;--shiki-default:#032F62;--shiki-sepia:#E6DB74"},"children":[{"type":"text","value":"\"SELECT first_name, last_name FROM employee\""}]},{"type":"element","tag":"span","props":{"style":"--shiki-dark:#E1E4E8;--shiki-default:#24292E;--shiki-sepia:#F8F8F2"},"children":[{"type":"text","value":")\n"}]}]},{"type":"element","tag":"span","props":{"class":"line","line":2},"children":[{"type":"element","tag":"span","props":{"style":"--shiki-dark:#E1E4E8;--shiki-dark-font-style:inherit;--shiki-default:#24292E;--shiki-default-font-style:inherit;--shiki-sepia:#66D9EF;--shiki-sepia-font-style:italic"},"children":[{"type":"text","value":"List"}]},{"type":"element","tag":"span","props":{"style":"--shiki-dark:#F97583;--shiki-default:#D73A49;--shiki-sepia:#F92672"},"children":[{"type":"text","value":"<"}]},{"type":"element","tag":"span","props":{"style":"--shiki-dark:#E1E4E8;--shiki-default:#24292E;--shiki-sepia:#F8F8F2"},"children":[{"type":"text","value":"Name"}]},{"type":"element","tag":"span","props":{"style":"--shiki-dark:#F97583;--shiki-default:#D73A49;--shiki-sepia:#F92672"},"children":[{"type":"text","value":">"}]},{"type":"element","tag":"span","props":{"style":"--shiki-dark:#B392F0;--shiki-default:#6F42C1;--shiki-sepia:#A6E22E"},"children":[{"type":"text","value":" getNames"}]},{"type":"element","tag":"span","props":{"style":"--shiki-dark:#E1E4E8;--shiki-default:#24292E;--shiki-sepia:#F8F8F2"},"children":[{"type":"text","value":"();\n"}]}]}]}]},{"type":"element","tag":"p","props":{},"children":[{"type":"text","value":"Тепер усе ок, і ми отримаємо список "},{"type":"element","tag":"code","props":{"className":[]},"children":[{"type":"text","value":"Name"}]},{"type":"text","value":" об'єктів."}]},{"type":"element","tag":"p","props":{},"children":[{"type":"text","value":"Ви також можете в цих не Entity класах використовувати вкладені класи з анотацією "},{"type":"element","tag":"code","props":{"className":[]},"children":[{"type":"text","value":"@Embedded"}]},{"type":"text","value":"."}]},{"type":"element","tag":"h2","props":{"id":"insert-update-і-delete-запити"},"children":[{"type":"text","value":"insert, update і delete запити"}]},{"type":"element","tag":"p","props":{},"children":[{"type":"text","value":"Анотації "},{"type":"element","tag":"code","props":{"className":[]},"children":[{"type":"text","value":"Insert"}]},{"type":"text","value":", "},{"type":"element","tag":"code","props":{"className":[]},"children":[{"type":"text","value":"Update"}]},{"type":"text","value":" і "},{"type":"element","tag":"code","props":{"className":[]},"children":[{"type":"text","value":"Delete"}]},{"type":"text","value":" дають нам змогу модифікувати дані, але їхні можливості занадто обмежені. Часто виникає необхідність оновити тільки деякі поля або видалити записи за певною умовою. Це можна зробити запитами за допомогою "},{"type":"element","tag":"code","props":{"className":[]},"children":[{"type":"text","value":"Query"}]},{"type":"text","value":"."}]},{"type":"element","tag":"p","props":{},"children":[{"type":"text","value":"Давайте розглянемо кілька прикладів."}]},{"type":"element","tag":"p","props":{},"children":[{"type":"text","value":"Оновлення зарплат у співробітників за списком id."}]},{"type":"element","tag":"pre","props":{"className":"language-java shiki shiki-themes github-dark github-light monokai","code":"@Query(\"UPDATE employee SET salary = :newSalary WHERE id IN (:idList)\")\nint updateSalaryByIdList(List<Long> idList, int newSalary);\n","language":"java","meta":"","style":""},"children":[{"type":"element","tag":"code","props":{"__ignoreMap":""},"children":[{"type":"element","tag":"span","props":{"class":"line","line":1},"children":[{"type":"element","tag":"span","props":{"style":"--shiki-dark:#E1E4E8;--shiki-default:#24292E;--shiki-sepia:#F8F8F2"},"children":[{"type":"text","value":"@"}]},{"type":"element","tag":"span","props":{"style":"--shiki-dark:#F97583;--shiki-dark-font-style:inherit;--shiki-default:#D73A49;--shiki-default-font-style:inherit;--shiki-sepia:#66D9EF;--shiki-sepia-font-style:italic"},"children":[{"type":"text","value":"Query"}]},{"type":"element","tag":"span","props":{"style":"--shiki-dark:#E1E4E8;--shiki-default:#24292E;--shiki-sepia:#F8F8F2"},"children":[{"type":"text","value":"("}]},{"type":"element","tag":"span","props":{"style":"--shiki-dark:#9ECBFF;--shiki-default:#032F62;--shiki-sepia:#E6DB74"},"children":[{"type":"text","value":"\"UPDATE employee SET salary = :newSalary WHERE id IN (:idList)\""}]},{"type":"element","tag":"span","props":{"style":"--shiki-dark:#E1E4E8;--shiki-default:#24292E;--shiki-sepia:#F8F8F2"},"children":[{"type":"text","value":")\n"}]}]},{"type":"element","tag":"span","props":{"class":"line","line":2},"children":[{"type":"element","tag":"span","props":{"style":"--shiki-dark:#F97583;--shiki-dark-font-style:inherit;--shiki-default:#D73A49;--shiki-default-font-style:inherit;--shiki-sepia:#66D9EF;--shiki-sepia-font-style:italic"},"children":[{"type":"text","value":"int"}]},{"type":"element","tag":"span","props":{"style":"--shiki-dark:#B392F0;--shiki-default:#6F42C1;--shiki-sepia:#A6E22E"},"children":[{"type":"text","value":" updateSalaryByIdList"}]},{"type":"element","tag":"span","props":{"style":"--shiki-dark:#E1E4E8;--shiki-default:#24292E;--shiki-sepia:#F8F8F2"},"children":[{"type":"text","value":"("}]},{"type":"element","tag":"span","props":{"style":"--shiki-dark:#E1E4E8;--shiki-dark-font-style:inherit;--shiki-default:#24292E;--shiki-default-font-style:inherit;--shiki-sepia:#66D9EF;--shiki-sepia-font-style:italic"},"children":[{"type":"text","value":"List"}]},{"type":"element","tag":"span","props":{"style":"--shiki-dark:#F97583;--shiki-default:#D73A49;--shiki-sepia:#F92672"},"children":[{"type":"text","value":"<"}]},{"type":"element","tag":"span","props":{"style":"--shiki-dark:#E1E4E8;--shiki-default:#24292E;--shiki-sepia:#F8F8F2"},"children":[{"type":"text","value":"Long"}]},{"type":"element","tag":"span","props":{"style":"--shiki-dark:#F97583;--shiki-default:#D73A49;--shiki-sepia:#F92672"},"children":[{"type":"text","value":">"}]},{"type":"element","tag":"span","props":{"style":"--shiki-dark:#E1E4E8;--shiki-default:#24292E;--shiki-sepia:#F8F8F2"},"children":[{"type":"text","value":" idList, "}]},{"type":"element","tag":"span","props":{"style":"--shiki-dark:#F97583;--shiki-dark-font-style:inherit;--shiki-default:#D73A49;--shiki-default-font-style:inherit;--shiki-sepia:#66D9EF;--shiki-sepia-font-style:italic"},"children":[{"type":"text","value":"int"}]},{"type":"element","tag":"span","props":{"style":"--shiki-dark:#E1E4E8;--shiki-default:#24292E;--shiki-sepia:#F8F8F2"},"children":[{"type":"text","value":" newSalary);\n"}]}]}]}]},{"type":"element","tag":"p","props":{},"children":[{"type":"text","value":"Опціонально метод може повертати "},{"type":"element","tag":"code","props":{"className":[]},"children":[{"type":"text","value":"int"}]},{"type":"text","value":" значення, в якому ми отримаємо кількість оновлених рядків. Якщо вам це не потрібно, то робіть метод void."}]},{"type":"element","tag":"p","props":{},"children":[{"type":"text","value":"Виклик методу матиме такий вигляд:"}]},{"type":"element","tag":"pre","props":{"className":"language-java shiki shiki-themes github-dark github-light monokai","code":"int updatedCount = db.employeeDao().updateSalaryByIdList(Arrays.asList(1L, 3L, 4L), 10000);\n","language":"java","meta":"","style":""},"children":[{"type":"element","tag":"code","props":{"__ignoreMap":""},"children":[{"type":"element","tag":"span","props":{"class":"line","line":1},"children":[{"type":"element","tag":"span","props":{"style":"--shiki-dark:#F97583;--shiki-dark-font-style:inherit;--shiki-default:#D73A49;--shiki-default-font-style:inherit;--shiki-sepia:#66D9EF;--shiki-sepia-font-style:italic"},"children":[{"type":"text","value":"int"}]},{"type":"element","tag":"span","props":{"style":"--shiki-dark:#E1E4E8;--shiki-default:#24292E;--shiki-sepia:#F8F8F2"},"children":[{"type":"text","value":" updatedCount "}]},{"type":"element","tag":"span","props":{"style":"--shiki-dark:#F97583;--shiki-default:#D73A49;--shiki-sepia:#F92672"},"children":[{"type":"text","value":"="}]},{"type":"element","tag":"span","props":{"style":"--shiki-dark:#E1E4E8;--shiki-default:#24292E;--shiki-sepia:#F8F8F2"},"children":[{"type":"text","value":" db."}]},{"type":"element","tag":"span","props":{"style":"--shiki-dark:#B392F0;--shiki-default:#6F42C1;--shiki-sepia:#A6E22E"},"children":[{"type":"text","value":"employeeDao"}]},{"type":"element","tag":"span","props":{"style":"--shiki-dark:#E1E4E8;--shiki-default:#24292E;--shiki-sepia:#F8F8F2"},"children":[{"type":"text","value":"()."}]},{"type":"element","tag":"span","props":{"style":"--shiki-dark:#B392F0;--shiki-default:#6F42C1;--shiki-sepia:#A6E22E"},"children":[{"type":"text","value":"updateSalaryByIdList"}]},{"type":"element","tag":"span","props":{"style":"--shiki-dark:#E1E4E8;--shiki-default:#24292E;--shiki-sepia:#F8F8F2"},"children":[{"type":"text","value":"(Arrays."}]},{"type":"element","tag":"span","props":{"style":"--shiki-dark:#B392F0;--shiki-default:#6F42C1;--shiki-sepia:#A6E22E"},"children":[{"type":"text","value":"asList"}]},{"type":"element","tag":"span","props":{"style":"--shiki-dark:#E1E4E8;--shiki-default:#24292E;--shiki-sepia:#F8F8F2"},"children":[{"type":"text","value":"("}]},{"type":"element","tag":"span","props":{"style":"--shiki-dark:#79B8FF;--shiki-default:#005CC5;--shiki-sepia:#AE81FF"},"children":[{"type":"text","value":"1L"}]},{"type":"element","tag":"span","props":{"style":"--shiki-dark:#E1E4E8;--shiki-default:#24292E;--shiki-sepia:#F8F8F2"},"children":[{"type":"text","value":", "}]},{"type":"element","tag":"span","props":{"style":"--shiki-dark:#79B8FF;--shiki-default:#005CC5;--shiki-sepia:#AE81FF"},"children":[{"type":"text","value":"3L"}]},{"type":"element","tag":"span","props":{"style":"--shiki-dark:#E1E4E8;--shiki-default:#24292E;--shiki-sepia:#F8F8F2"},"children":[{"type":"text","value":", "}]},{"type":"element","tag":"span","props":{"style":"--shiki-dark:#79B8FF;--shiki-default:#005CC5;--shiki-sepia:#AE81FF"},"children":[{"type":"text","value":"4L"}]},{"type":"element","tag":"span","props":{"style":"--shiki-dark:#E1E4E8;--shiki-default:#24292E;--shiki-sepia:#F8F8F2"},"children":[{"type":"text","value":"), "}]},{"type":"element","tag":"span","props":{"style":"--shiki-dark:#79B8FF;--shiki-default:#005CC5;--shiki-sepia:#AE81FF"},"children":[{"type":"text","value":"10000"}]},{"type":"element","tag":"span","props":{"style":"--shiki-dark:#E1E4E8;--shiki-default:#24292E;--shiki-sepia:#F8F8F2"},"children":[{"type":"text","value":");\n"}]}]}]}]},{"type":"element","tag":"p","props":{},"children":[{"type":"text","value":"Видалення співробітників за списком id"}]},{"type":"element","tag":"pre","props":{"className":"language-java shiki shiki-themes github-dark github-light monokai","code":"@Query(\"DELETE from employee WHERE id IN (:idList)\")\nint deleteByIdList(List<Long> idList);\n","language":"java","meta":"","style":""},"children":[{"type":"element","tag":"code","props":{"__ignoreMap":""},"children":[{"type":"element","tag":"span","props":{"class":"line","line":1},"children":[{"type":"element","tag":"span","props":{"style":"--shiki-dark:#E1E4E8;--shiki-default:#24292E;--shiki-sepia:#F8F8F2"},"children":[{"type":"text","value":"@"}]},{"type":"element","tag":"span","props":{"style":"--shiki-dark:#F97583;--shiki-dark-font-style:inherit;--shiki-default:#D73A49;--shiki-default-font-style:inherit;--shiki-sepia:#66D9EF;--shiki-sepia-font-style:italic"},"children":[{"type":"text","value":"Query"}]},{"type":"element","tag":"span","props":{"style":"--shiki-dark:#E1E4E8;--shiki-default:#24292E;--shiki-sepia:#F8F8F2"},"children":[{"type":"text","value":"("}]},{"type":"element","tag":"span","props":{"style":"--shiki-dark:#9ECBFF;--shiki-default:#032F62;--shiki-sepia:#E6DB74"},"children":[{"type":"text","value":"\"DELETE from employee WHERE id IN (:idList)\""}]},{"type":"element","tag":"span","props":{"style":"--shiki-dark:#E1E4E8;--shiki-default:#24292E;--shiki-sepia:#F8F8F2"},"children":[{"type":"text","value":")\n"}]}]},{"type":"element","tag":"span","props":{"class":"line","line":2},"children":[{"type":"element","tag":"span","props":{"style":"--shiki-dark:#F97583;--shiki-dark-font-style:inherit;--shiki-default:#D73A49;--shiki-default-font-style:inherit;--shiki-sepia:#66D9EF;--shiki-sepia-font-style:italic"},"children":[{"type":"text","value":"int"}]},{"type":"element","tag":"span","props":{"style":"--shiki-dark:#B392F0;--shiki-default:#6F42C1;--shiki-sepia:#A6E22E"},"children":[{"type":"text","value":" deleteByIdList"}]},{"type":"element","tag":"span","props":{"style":"--shiki-dark:#E1E4E8;--shiki-default:#24292E;--shiki-sepia:#F8F8F2"},"children":[{"type":"text","value":"("}]},{"type":"element","tag":"span","props":{"style":"--shiki-dark:#E1E4E8;--shiki-dark-font-style:inherit;--shiki-default:#24292E;--shiki-default-font-style:inherit;--shiki-sepia:#66D9EF;--shiki-sepia-font-style:italic"},"children":[{"type":"text","value":"List"}]},{"type":"element","tag":"span","props":{"style":"--shiki-dark:#F97583;--shiki-default:#D73A49;--shiki-sepia:#F92672"},"children":[{"type":"text","value":"<"}]},{"type":"element","tag":"span","props":{"style":"--shiki-dark:#E1E4E8;--shiki-default:#24292E;--shiki-sepia:#F8F8F2"},"children":[{"type":"text","value":"Long"}]},{"type":"element","tag":"span","props":{"style":"--shiki-dark:#F97583;--shiki-default:#D73A49;--shiki-sepia:#F92672"},"children":[{"type":"text","value":">"}]},{"type":"element","tag":"span","props":{"style":"--shiki-dark:#E1E4E8;--shiki-default:#24292E;--shiki-sepia:#F8F8F2"},"children":[{"type":"text","value":" idList);\n"}]}]}]}]},{"type":"element","tag":"p","props":{},"children":[{"type":"text","value":"Запити видалення також можуть повертати "},{"type":"element","tag":"code","props":{"className":[]},"children":[{"type":"text","value":"int"}]},{"type":"text","value":" значення, в якому ми отримаємо кількість видалених рядків."}]},{"type":"element","tag":"p","props":{},"children":[{"type":"text","value":"Виклик методу:"}]},{"type":"element","tag":"pre","props":{"className":"language-java shiki shiki-themes github-dark github-light monokai","code":"int deletedCount = db.employeeDao().deleteByIdList(Arrays.asList(1L, 3L, 4L));\n","language":"java","meta":"","style":""},"children":[{"type":"element","tag":"code","props":{"__ignoreMap":""},"children":[{"type":"element","tag":"span","props":{"class":"line","line":1},"children":[{"type":"element","tag":"span","props":{"style":"--shiki-dark:#F97583;--shiki-dark-font-style:inherit;--shiki-default:#D73A49;--shiki-default-font-style:inherit;--shiki-sepia:#66D9EF;--shiki-sepia-font-style:italic"},"children":[{"type":"text","value":"int"}]},{"type":"element","tag":"span","props":{"style":"--shiki-dark:#E1E4E8;--shiki-default:#24292E;--shiki-sepia:#F8F8F2"},"children":[{"type":"text","value":" deletedCount "}]},{"type":"element","tag":"span","props":{"style":"--shiki-dark:#F97583;--shiki-default:#D73A49;--shiki-sepia:#F92672"},"children":[{"type":"text","value":"="}]},{"type":"element","tag":"span","props":{"style":"--shiki-dark:#E1E4E8;--shiki-default:#24292E;--shiki-sepia:#F8F8F2"},"children":[{"type":"text","value":" db."}]},{"type":"element","tag":"span","props":{"style":"--shiki-dark:#B392F0;--shiki-default:#6F42C1;--shiki-sepia:#A6E22E"},"children":[{"type":"text","value":"employeeDao"}]},{"type":"element","tag":"span","props":{"style":"--shiki-dark:#E1E4E8;--shiki-default:#24292E;--shiki-sepia:#F8F8F2"},"children":[{"type":"text","value":"()."}]},{"type":"element","tag":"span","props":{"style":"--shiki-dark:#B392F0;--shiki-default:#6F42C1;--shiki-sepia:#A6E22E"},"children":[{"type":"text","value":"deleteByIdList"}]},{"type":"element","tag":"span","props":{"style":"--shiki-dark:#E1E4E8;--shiki-default:#24292E;--shiki-sepia:#F8F8F2"},"children":[{"type":"text","value":"(Arrays."}]},{"type":"element","tag":"span","props":{"style":"--shiki-dark:#B392F0;--shiki-default:#6F42C1;--shiki-sepia:#A6E22E"},"children":[{"type":"text","value":"asList"}]},{"type":"element","tag":"span","props":{"style":"--shiki-dark:#E1E4E8;--shiki-default:#24292E;--shiki-sepia:#F8F8F2"},"children":[{"type":"text","value":"("}]},{"type":"element","tag":"span","props":{"style":"--shiki-dark:#79B8FF;--shiki-default:#005CC5;--shiki-sepia:#AE81FF"},"children":[{"type":"text","value":"1L"}]},{"type":"element","tag":"span","props":{"style":"--shiki-dark:#E1E4E8;--shiki-default:#24292E;--shiki-sepia:#F8F8F2"},"children":[{"type":"text","value":", "}]},{"type":"element","tag":"span","props":{"style":"--shiki-dark:#79B8FF;--shiki-default:#005CC5;--shiki-sepia:#AE81FF"},"children":[{"type":"text","value":"3L"}]},{"type":"element","tag":"span","props":{"style":"--shiki-dark:#E1E4E8;--shiki-default:#24292E;--shiki-sepia:#F8F8F2"},"children":[{"type":"text","value":", "}]},{"type":"element","tag":"span","props":{"style":"--shiki-dark:#79B8FF;--shiki-default:#005CC5;--shiki-sepia:#AE81FF"},"children":[{"type":"text","value":"4L"}]},{"type":"element","tag":"span","props":{"style":"--shiki-dark:#E1E4E8;--shiki-default:#24292E;--shiki-sepia:#F8F8F2"},"children":[{"type":"text","value":"));\n"}]}]}]}]},{"type":"element","tag":"style","props":{},"children":[{"type":"text","value":"html .dark .shiki span {color: var(--shiki-dark);background: var(--shiki-dark-bg);font-style: var(--shiki-dark-font-style);font-weight: var(--shiki-dark-font-weight);text-decoration: var(--shiki-dark-text-decoration);}html.dark .shiki span {color: var(--shiki-dark);background: var(--shiki-dark-bg);font-style: var(--shiki-dark-font-style);font-weight: var(--shiki-dark-font-weight);text-decoration: var(--shiki-dark-text-decoration);}html .default .shiki span {color: var(--shiki-default);background: var(--shiki-default-bg);font-style: var(--shiki-default-font-style);font-weight: var(--shiki-default-font-weight);text-decoration: var(--shiki-default-text-decoration);}html .shiki span {color: var(--shiki-default);background: var(--shiki-default-bg);font-style: var(--shiki-default-font-style);font-weight: var(--shiki-default-font-weight);text-decoration: var(--shiki-default-text-decoration);}html .sepia .shiki span {color: var(--shiki-sepia);background: var(--shiki-sepia-bg);font-style: var(--shiki-sepia-font-style);font-weight: var(--shiki-sepia-font-weight);text-decoration: var(--shiki-sepia-text-decoration);}html.sepia .shiki span {color: var(--shiki-sepia);background: var(--shiki-sepia-bg);font-style: var(--shiki-sepia-font-style);font-weight: var(--shiki-sepia-font-weight);text-decoration: var(--shiki-sepia-text-decoration);}"}]}],"toc":{"title":"","searchDepth":2,"depth":2,"links":[{"id":"list-масив-cursor","depth":2,"text":"List, масив, Cursor"},{"id":"передача-параметрів","depth":2,"text":"Передача параметрів"},{"id":"subsets","depth":2,"text":"Subsets"},{"id":"insert-update-і-delete-запити","depth":2,"text":"insert, update і delete запити"}]}},"_type":"markdown","_id":"content:1.android:7.lesson7:4.query.md","_source":"content","_file":"1.android/7.lesson7/4.query.md","_stem":"1.android/7.lesson7/4.query","_extension":"md"}